rdfc_log_processor/__init__.py
rdfc_log_processor/processor.py
rdfc_log_processor/processor.ttl
rdfc_log_processor-0.0.1.dist-info/METADATA
rdfc_log_processor-0.0.1.dist-info/WHEEL
rdfc_log_processor-0.0.1.dist-info/RECORD
