Metadata-Version: 2.4
Name: rdfc_log-processor
Version: 0.0.1
Summary: A simple Python processor to log an incoming stream to the console.
Project-URL: Homepage, https://rdf-connect.github.io
Project-URL: Repository, https://github.com/rdf-connect/log-processor-py
Project-URL: Issues, https://github.com/rdf-connect/log-processor-/issues
Author-email: Ieben Smessaert <ieben.smessaert@ugent.be>
License-Expression: MIT
Requires-Python: >=3.12
Requires-Dist: pytest-asyncio>=1.1.0
Requires-Dist: pytest>=8.4.1
Requires-Dist: rdfc-proto>=0.0.1
Requires-Dist: rdfc-runner>=0.0.1
